ycast/__init__.py
ycast/__main__.py
ycast/generic.py
ycast/my_stations.py
ycast/radiobrowser.py
ycast/server.py
ycast/station_icons.py
ycast/vtuner.py
ycast-1.1.0.dist-info/LICENSE.txt
ycast-1.1.0.dist-info/METADATA
ycast-1.1.0.dist-info/WHEEL
ycast-1.1.0.dist-info/top_level.txt
ycast-1.1.0.dist-info/RECORD
