Metadata-Version: 2.1
Name: ycast
Version: 1.1.0
Summary: Self hosted vTuner internet radio service emulation
Home-page: https://github.com/milaq/YCast
Author: milaq
Author-email: micha.laqua@gmail.com
License: GPLv3
Keywords: ycast,streaming,vtuner,internet radio,music,radio,shoutcast,avr,emulation,yamaha,onkyo,denon
Platform: UNKNOWN
Classifier: Development Status :: 4 - Beta
Classifier: Intended Audience :: Developers
Classifier: Intended Audience :: System Administrators
Classifier: License :: OSI Approved :: GNU General Public License v3 (GPLv3)
Classifier: Natural Language :: English
Classifier: Operating System :: POSIX :: Linux
Classifier: Programming Language :: Python :: 3
Classifier: Topic :: Multimedia :: Sound/Audio
Classifier: Topic :: Software Development :: Libraries :: Python Modules
Requires-Dist: requests
Requires-Dist: flask
Requires-Dist: PyYAML
Requires-Dist: Pillow
